LICENSE.txt
MANIFEST.in
README.rst
setup.py
treeutils/__init__.py
treeutils.egg-info/PKG-INFO
treeutils.egg-info/SOURCES.txt
treeutils.egg-info/dependency_links.txt
treeutils.egg-info/top_level.txt