Metadata-Version: 1.1
Name: treeutils
Version: 0.1.0
Summary: For developers who have to fit real world data into tree structures like the D3 tree.
Home-page: https://github.com/Charles-Kaminski/treeutils
Author: Charles Kaminski
Author-email: CharlesKaminski@gmail.com
License: BSD 3-Clause License
Keywords: Tree,Cluster,Parent,Child,Branch,Root,D3
Platform: UNKNOWN
Classifier: Development Status :: 5 - Production/Stable
Classifier: Intended Audience :: Developers
Classifier: License :: OSI Approved :: BSD License
Classifier: Operating System :: OS Independent
Classifier: Programming Language :: Python
Classifier: Programming Language :: Python :: 2
Classifier: Programming Language :: Python :: 2.7
Classifier: Programming Language :: Python :: 3
Classifier: Topic :: Sociology
Classifier: Topic :: Scientific/Engineering
Classifier: Topic :: Scientific/Engineering :: Visualization
Classifier: Topic :: Utilities
